{
  "main": {
    "id": "6fb6faa5b5ca7449",
    "type": "split",
    "children": [
      {
        "id": "de3df3e5a4a7f8f9",
        "type": "tabs",
        "children": [
          {
            "id": "e8520d3415809b58",
            "type": "leaf",
            "state": {
              "type": "markdown",
              "state": {
                "file": "stories/Shadows_in_Buckhead/chapter_summary.md",
                "mode": "source",
                "source": false
              }
            }
          }
        ]
      }
    ],
    "direction": "vertical"
  },
  "left": {
    "id": "aa741008feff410f",
    "type": "split",
    "children": [
      {
        "id": "64f9dc521defe92a",
        "type": "tabs",
        "children": [
          {
            "id": "33fbe4356a9ed082",
            "type": "leaf",
            "state": {
              "type": "file-explorer",
              "state": {
                "sortOrder": "alphabetical"
              }
            }
          },
          {
            "id": "45cc05aec388333b",
            "type": "leaf",
            "state": {
              "type": "search",
              "state": {
                "query": "",
                "matchingCase": false,
                "explainSearch": false,
                "collapseAll": false,
                "extraContext": false,
                "sortOrder": "alphabetical"
              }
            }
          },
          {
            "id": "c4fa31ab747deae3",
            "type": "leaf",
            "state": {
              "type": "bookmarks",
              "state": {}
            }
          }
        ]
      }
    ],
    "direction": "horizontal",
    "width": 300
  },
  "right": {
    "id": "c31be9d1c11467b6",
    "type": "split",
    "children": [
      {
        "id": "b07dcfe21cd0fb0c",
        "type": "tabs",
        "children": [
          {
            "id": "d97425f4ad4e900a",
            "type": "leaf",
            "state": {
              "type": "backlink",
              "state": {
                "file": "stories/Shadows_in_Buckhead/chapter_summary.md",
                "collapseAll": false,
                "extraContext": false,
                "sortOrder": "alphabetical",
                "showSearch": false,
                "searchQuery": "",
                "backlinkCollapsed": false,
                "unlinkedCollapsed": true
              }
            }
          },
          {
            "id": "f20ed7515b406c09",
            "type": "leaf",
            "state": {
              "type": "outgoing-link",
              "state": {
                "file": "stories/Shadows_in_Buckhead/chapter_summary.md",
                "linksCollapsed": false,
                "unlinkedCollapsed": true
              }
            }
          },
          {
            "id": "22f8a83b7b1ca0e2",
            "type": "leaf",
            "state": {
              "type": "tag",
              "state": {
                "sortOrder": "frequency",
                "useHierarchy": true
              }
            }
          },
          {
            "id": "62ba8e6dc1e74ff3",
            "type": "leaf",
            "state": {
              "type": "outline",
              "state": {
                "file": "stories/Shadows_in_Buckhead/chapter_summary.md"
              }
            }
          }
        ]
      }
    ],
    "direction": "horizontal",
    "width": 300,
    "collapsed": true
  },
  "left-ribbon": {
    "hiddenItems": {
      "switcher:Open quick switcher": false,
      "graph:Open graph view": false,
      "canvas:Create new canvas": false,
      "daily-notes:Open today's daily note": false,
      "templates:Insert template": false,
      "command-palette:Open command palette": false
    }
  },
  "active": "e8520d3415809b58",
  "lastOpenFiles": [
    "stories/Shadows_in_Buckhead/assets/narrative_outline.md",
    "stories/Shadows_in_Buckhead/chapter_summary.md",
    "stories/Shadows_in_Buckhead/opening_scene.md",
    "stories/Bound_by_Desire/opening_scene.md",
    "stories/Bound_by_Desire/chapter_summary_summary.md",
    "stories/Bound_by_Desire/chapter_summary.md",
    "stories/Bound_by_Desire/assets/writing_style_summary.md",
    "stories/Bound_by_Desire/assets/writing_style.md",
    "stories/Bound_by_Desire/writing_style.md",
    "stories/Bound_by_Desire/assets/narrative_outline_summary.md",
    "stories/Bound_by_Desire/assets/narrative_outline.md",
    "stories/Bound_by_Desire/assets",
    "stories/Bound_by_Desire/plot_outline.md",
    "stories/Bound_by_Desire/concept.md",
    "stories/Bound_by_Desire",
    "stories/Canine_Crusoe/opening_scene.md",
    "stories/Shadows_in_Buckhead/chapter_summary_summary.md",
    "stories/Shadows_in_Buckhead/assets/writing_style_summary.md",
    "stories/Shadows_in_Buckhead/assets/writing_style.md",
    "stories/Shadows_in_Buckhead/writing_style.md",
    "stories/Shadows_in_Buckhead/assets/narrative_outline_summary.md",
    "stories/Shadows_in_Buckhead/assets",
    "stories/Shadows_in_Buckhead/plot_outline.md",
    "stories/Shadows_in_Buckhead/concept.md",
    "stories/Shadows_in_Buckhead",
    "todos.md",
    "stories/Canine_Crusoe/chapter_summary_summary.md",
    "stories/Canine_Crusoe/chapter_summary.md",
    "stories/Canine_Crusoe/assets/writing_style_summary.md",
    "stories/Canine_Crusoe/assets/writing_style.md",
    "stories/Canine_Crusoe/assets",
    "stories/Canine_Crusoe",
    "stories/Threads_of_Time/assets",
    "stories/Threads_of_Time",
    "stories/The_Echo_of_Shadows/assets",
    "stories/The_Echo_of_Shadows"
  ]
}